ports/__init__.py
ports.py-0.6.0.dist-info/METADATA
ports.py-0.6.0.dist-info/WHEEL
ports.py-0.6.0.dist-info/top_level.txt
ports.py-0.6.0.dist-info/RECORD
