Metadata-Version: 2.1
Name: ports.py
Version: 0.6.0
Summary: A modern webserver, check github for more information
Home-page: http://github.com/n30nyx/ports
Author: n30nyx/Sakurai07
Author-email: blzzardst0rm@gmail.com
License: MIT
Keywords: webserver,flask alternative,ports
Classifier: Programming Language :: Python :: 3
Requires-Dist: socket
Requires-Dist: requests
Requires-Dist: sqlite3
Requires-Dist: websockets
